<?xml version="1.0" encoding="UTF-8"?>
<OTA_CourseSearchRS xmlns="http://www.opentravel.org/OTA" xmlns:xsi="http://www.w3.org/2001/XMLSchema-instance" xsi:schemaLocation="http://www.opentravel.org/OTA OTA_CourseSearchRS.xsd" EchoToken="12345" TimeStamp="1999-05-31T13:20:00-05:00" Target="Production" Version="2001C" SequenceNmbr="123456" DetailResponse="true">
	<Success/>
	<GolfCourse Id="FL1234" Name="Sea Grass Golf Resort" City="Jupiter" State="FL" Country="USA" PostalCode="21921" County="Palm Beach" Province="" PhoneNumber="444 444-4444">
		<Trait Name="Architect" Value="Robert Trent Jones"/>
		<Trait Name="Singles Confirmed" Value="Yes"/>
		<Trait Name="ADA Challenged" Value="Wheelchair"/>
		<Trait Name="Slope" Value="110"/>
		<Trait Name="Metal Spikes" Value="No"/>
		<Trait Name="Caddies Available" Value="No"/>
		<Trait Name="Yardage" Value="6345"/>
		<Trait Name="Personal Carts Permitted" Value="No"/>
		<Trait Name="Fivesome" Value="No"/>
		<Trait Name="GrassType" Value="Bermuda"/>
	</GolfCourse>
	<GolfCourse Id="FL4321" Name="Beach Side Golf Resort" City="Palm Beach Gardens" State="FL" Country="USA" PostalCode="21932" County="Palm Beach" Province="" PhoneNumber="555 555-5555">
		<Trait Name="Architect" Value="Jack Nicklaus"/>
		<Trait Name="Singles Confirmed" Value="Yes"/>
		<Trait Name="ADA Challenged" Value="Blind"/>
		<Trait Name="Slope" Value="112"/>
		<Trait Name="Metal Spikes" Value="Yes"/>
		<Trait Name="Caddies Available" Value="Yes"/>
		<Trait Name="Yardage" Value="7102"/>
		<Trait Name="Fivesome" Value="Yes"/>
		<Trait Name="GrassType" Value="Rye"/>
	</GolfCourse>
</OTA_CourseSearchRS>
